{
  "kind": "singleType",
  "collectionName": "site_settings",
  "info": {
    "singularName": "site-setting",
    "pluralName": "site-settings",
    "displayName": "Site settings",
    "description": ""
  },
  "options": {
    "draftAndPublish": true
  },
  "pluginOptions": {},
  "attributes": {
    "title": {
      "type": "string",
      "maxLength": 255,
      "required": true
    },
    "description": {
      "type": "text",
      "maxLength": 1000
    },
    "logo": {
      "type": "string",
      "maxLength": 255
    },
    "favicon": {
      "type": "string",
      "maxLength": 255
    },
    "meta_keywords": {
      "type": "string"
    },
    "meta_description": {
      "type": "text"
    },
    "facebook_url": {
      "type": "string",
      "maxLength": 255
    },
    "x_url": {
      "type": "string",
      "maxLength": 255
    },
    "instagram_url": {
      "type": "string",
      "maxLength": 255
    },
    "youtube_url": {
      "type": "string",
      "maxLength": 255
    },
    "contact_email": {
      "type": "string",
      "maxLength": 255
    },
    "contact_phone": {
      "type": "string",
      "maxLength": 20
    },
    "address": {
      "type": "string",
      "maxLength": 500
    },
    "meta_title": {
      "type": "string",
      "required": false
    }
  }
}
